Metadata-Version: 2.1
Name: geotifflib
Version: 0.0.4
Summary: A Python GeoTiff kit based on GDAL
Home-page: https://github.com/Flemyng1999/geotifflib
Author: flemyng feng
Author-email: flemyng1999@outlook.com
Keywords: python,tiff,geotiff,windows,mac,linux
Classifier: Programming Language :: Python :: 3
Classifier: License :: OSI Approved :: Apache Software License
Classifier: Operating System :: OS Independent
Requires-Python: >=3.9
License-File: LICENSE
Requires-Dist: numpy
